{
  "_id": "GWec40ev4OEYJiKv",
  "displayRoll": true,
  "flags": {
    "core": {
      "sourceId": "RollTable.AvC3j0ITIr6hX7oH"
    }
  },
  "folder": null,
  "formula": "1d6",
  "img": "systems/zweihander/assets/icons/deadly-strike.svg",
  "name": "Grievous Injuries",
  "permission": {
    "JyjuBRFhP4y9QWxg": 3,
    "default": 0
  },
  "replacement": true,
  "results": [
    {
      "_id": "FAwkopnhHGfQXGdC",
      "collection": "zweihander.zh-injuries",
      "drawn": false,
      "flags": {},
      "img": "systems/zweihander/assets/icons/knee-cap.svg",
      "range": [
        1,
        1
      ],
      "rangeH": 1,
      "rangeL": 1,
      "resultId": "r4qzv0fHhhu0ckpe",
      "text": "Hobbled",
      "type": 2,
      "weight": 1
    },
    {
      "_id": "SMRiWqb38mVGpv41",
      "collection": "zweihander.zh-injuries",
      "drawn": false,
      "flags": {},
      "img": "systems/zweihander/assets/icons/liver.svg",
      "range": [
        2,
        2
      ],
      "rangeH": 2,
      "rangeL": 2,
      "resultId": "wElNhbMVwgu8fjwB",
      "text": "Impaled",
      "type": 2,
      "weight": 1
    },
    {
      "_id": "R65sLpRPgtsFHOLJ",
      "collection": "zweihander.zh-injuries",
      "drawn": false,
      "flags": {},
      "img": "systems/zweihander/assets/icons/hand-bandage.svg",
      "range": [
        3,
        3
      ],
      "rangeH": 3,
      "rangeL": 3,
      "resultId": "sbkHr3HNHmfhUwFR",
      "text": "Shattered Hand",
      "type": 2,
      "weight": 1
    },
    {
      "_id": "U5Bw0ydtKt0HiIfb",
      "collection": "zweihander.zh-injuries",
      "drawn": false,
      "flags": {},
      "img": "systems/zweihander/assets/icons/elbow-pad.svg",
      "range": [
        4,
        4
      ],
      "rangeH": 4,
      "rangeL": 4,
      "resultId": "KZLB7QKIHr7D4IuJ",
      "text": "Compound Fracture",
      "type": 2,
      "weight": 1
    },
    {
      "_id": "6qbp3UGuP2KPq2vO",
      "collection": "zweihander.zh-injuries",
      "drawn": false,
      "flags": {},
      "img": "systems/zweihander/assets/icons/nose-side.svg",
      "range": [
        5,
        5
      ],
      "rangeH": 5,
      "rangeL": 5,
      "resultId": "fE5tcMGwEpvFXfwM",
      "text": "Ruined Jaw",
      "type": 2,
      "weight": 1
    },
    {
      "_id": "rtPr45ynudauWQhB",
      "collection": "zweihander.zh-injuries",
      "drawn": false,
      "flags": {},
      "img": "systems/zweihander/assets/icons/blood.svg",
      "range": [
        6,
        6
      ],
      "rangeH": 6,
      "rangeL": 6,
      "resultId": "aXbrII21DCJw4XvK",
      "text": "Arterial Spray",
      "type": 2,
      "weight": 1
    }
  ],
  "sort": 0
}
